ordinal_xai/__init__.py
ordinal_xai/__main__.py
ordinal_xai/requirements.txt
ordinal_xai/data/FI_test.csv
ordinal_xai/data/abalone.csv
ordinal_xai/data/automobile.csv
ordinal_xai/data/balance_scale.csv
ordinal_xai/data/car_evaluation.csv
ordinal_xai/data/dummy.csv
ordinal_xai/data/student-mat.csv
ordinal_xai/data/student-por.csv
ordinal_xai/data/winequality-red.csv
ordinal_xai/data/winequality-white.csv
ordinal_xai/data/winequality.csv
ordinal_xai/interpretation/__init__.py
ordinal_xai/interpretation/base_interpretation.py
ordinal_xai/interpretation/ice.py
ordinal_xai/interpretation/ice_prob.py
ordinal_xai/interpretation/lime.py
ordinal_xai/interpretation/loco.py
ordinal_xai/interpretation/pdp.py
ordinal_xai/interpretation/pdp_prob.py
ordinal_xai/interpretation/pfi.py
ordinal_xai/models/__init__.py
ordinal_xai/models/base_model.py
ordinal_xai/models/clm.py
ordinal_xai/models/obd.py
ordinal_xai/models/ogboost.py
ordinal_xai/models/onn.py
ordinal_xai/utils/__init__.py
ordinal_xai/utils/_response_modified.py
ordinal_xai/utils/data_utils.py
ordinal_xai/utils/evaluation_metrics.py
ordinal_xai/utils/pdp_modified.py
ordinal_xai-0.2.1.dist-info/licenses/LICENSE
ordinal_xai-0.2.1.dist-info/METADATA
ordinal_xai-0.2.1.dist-info/WHEEL
ordinal_xai-0.2.1.dist-info/top_level.txt
ordinal_xai-0.2.1.dist-info/RECORD
